Metadata-Version: 1.0
Name: mdn-mark
Version: 1.3.5
Summary: 采集百度手机卫士 360手机卫士 搜狗号码通三个平台对手机号码的标注信息.
Home-page: UNKNOWN
Author: 陈忠润
Author-email: chenzhongrun@bonc.com.cn
License: UNKNOWN
Platform: UNKNOWN
